holboxai_health/__init__.py
holboxai_health/aws_auth.py
holboxai_health/cli.py
holboxai_health/transcribe.py
holboxai_health-0.1.1.dist-info/METADATA
holboxai_health-0.1.1.dist-info/WHEEL
holboxai_health-0.1.1.dist-info/entry_points.txt
holboxai_health-0.1.1.dist-info/top_level.txt
holboxai_health-0.1.1.dist-info/RECORD
